color_changer-1.0.5.dist-info/DESCRIPTION.rst
color_changer-1.0.5.dist-info/METADATA
color_changer-1.0.5.dist-info/RECORD
color_changer-1.0.5.dist-info/WHEEL
color_changer-1.0.5.dist-info/metadata.json
color_changer-1.0.5.dist-info/top_level.txt
colorchanger/__init__.py
colorchanger/app.py
colorchanger/colorchanger.py
