Metadata-Version: 2.0
Name: color-changer
Version: 1.0.5
Summary: Reads in an image and swap specified colors 
Home-page: https://github.com/DahlitzFlorian/python-color-changer
Author: Florian Dahlitz
Author-email: f2dahlitz@freenet.de
License: MIT
Keywords: color changer color-changer opencv numpy
Platform: UNKNOWN
Classifier: Development Status :: 5 - Production/Stable
Classifier: Intended Audience :: Developers
Classifier: License :: OSI Approved :: MIT License
Classifier: Programming Language :: Python :: 3.4
Classifier: Programming Language :: Python :: 3.5
Classifier: Programming Language :: Python :: 3.6
Requires-Dist: click
Requires-Dist: numpy
